binalyzer_data_provider/__init__.py
binalyzer_data_provider/cli.py
binalyzer_data_provider/io.py
binalyzer_data_provider-1.0.0.data/data/CHANGELOG.md
binalyzer_data_provider-1.0.0.dist-info/AUTHORS
binalyzer_data_provider-1.0.0.dist-info/LICENSE.rst
binalyzer_data_provider-1.0.0.dist-info/METADATA
binalyzer_data_provider-1.0.0.dist-info/WHEEL
binalyzer_data_provider-1.0.0.dist-info/top_level.txt
binalyzer_data_provider-1.0.0.dist-info/RECORD
